communal/__init__.py
communal/attrdict.py
communal/binary.py
communal/casing.py
communal/client.py
communal/collections.py
communal/dates.py
communal/download.py
communal/encoding.py
communal/enum.py
communal/exceptions.py
communal/files.py
communal/floats.py
communal/functions.py
communal/getter.py
communal/guids.py
communal/hashing.py
communal/http.py
communal/inflections.py
communal/inheritance.py
communal/ips.py
communal/iterables.py
communal/memory.py
communal/mixins.py
communal/nesting.py
communal/nulls.py
communal/properties.py
communal/sets.py
communal/sizes.py
communal/submodules.py
communal/time_periods.py
communal/timezone.py
communal/tracebacks.py
communal/zip_archive.py
communal-0.5.1.dist-info/METADATA
communal-0.5.1.dist-info/WHEEL
communal-0.5.1.dist-info/licenses/LICENSE
communal-0.5.1.dist-info/RECORD
